testyourmodel/__init__.py
testyourmodel/foo.py
testyourmodel-0.0.1.dist-info/METADATA
testyourmodel-0.0.1.dist-info/WHEEL
testyourmodel-0.0.1.dist-info/licenses/LICENSE
testyourmodel-0.0.1.dist-info/RECORD
