Metadata-Version: 2.4
Name: testyourmodel
Version: 0.0.1
Summary: This is a template repository for Python projects that use uv for their dependency management.
Project-URL: Homepage, https://niklub.github.io/testyourmodel/
Project-URL: Repository, https://github.com/niklub/testyourmodel
Project-URL: Documentation, https://niklub.github.io/testyourmodel/
Author-email: HumanSignal <hi@humansignal.com>
License-File: LICENSE
Keywords: python
Classifier: Intended Audience :: Developers
Classifier: Programming Language :: Python
Classifier: Programming Language :: Python :: 3
Classifier: Programming Language :: Python :: 3.9
Classifier: Programming Language :: Python :: 3.10
Classifier: Programming Language :: Python :: 3.11
Classifier: Programming Language :: Python :: 3.12
Classifier: Programming Language :: Python :: 3.13
Classifier: Topic :: Software Development :: Libraries :: Python Modules
Requires-Python: <4.0,>=3.9
